{
  "appPageId" : "68919fd6-cacb-4f97-b48a-818be19f40ac",
  "componentName" : "siteforce:sldsTwoCol84Layout",
  "id" : "f41d1d26-f189-4ee6-8c1f-92e9846ff47e",
  "label" : "Question Detail",
  "regions" : [ {
    "components" : [ {
      "componentAttributes" : {
        "bannerText" : "",
        "bannerTextWithKnowledge" : "Explore other <a href=\"javascript:void(0)\" class=\"headlineArticles\">articles</a> and <a href=\"javascript:void(0)\" class=\"headlineDiscussions\">discussions</a> on this topic.",
        "bannerTextWithoutKnowledge" : "Explore other <a href=\"javascript:void(0)\" class=\"headlineDiscussions\">discussions</a> on this topic.",
        "pageType" : "discussion",
        "showSubTopics" : true,
        "title" : "Welcome!",
        "uniqueNameOrId" : "{!recordId}"
      },
      "componentName" : "forceCommunity:headline",
      "id" : "a5e46850-6931-4e9e-941c-bf204f03454e",
      "renderPriority" : "NEUTRAL",
      "renditionMap" : { },
      "type" : "component"
    } ],
    "id" : "da22f0e7-1dd8-4bdf-ab58-ba9031806f83",
    "regionName" : "header",
    "type" : "region"
  }, {
    "components" : [ {
      "componentAttributes" : {
        "id" : "{!feedItemId}"
      },
      "componentName" : "forceCommunity:feedItemDetail",
      "id" : "92c8ba49-df4b-4ac5-9948-f163193af71b",
      "renderPriority" : "NEUTRAL",
      "renditionMap" : { },
      "type" : "component"
    } ],
    "id" : "abfdabd7-4844-4588-8132-b75a6cb50fd2",
    "regionName" : "content",
    "type" : "region"
  }, {
    "components" : [ {
      "componentAttributes" : {
        "numberOfItems" : 5,
        "showViewCounts" : true,
        "title" : "Related Questions"
      },
      "componentName" : "selfService:similarQuestions",
      "id" : "bf19e71e-3831-4daa-9a69-299dab347e52",
      "renderPriority" : "NEUTRAL",
      "renditionMap" : { },
      "type" : "component"
    }, {
      "componentAttributes" : {
        "channel" : "DefaultChannel",
        "title" : ""
      },
      "componentName" : "forceCommunity:recommendations",
      "id" : "f255c8c4-8519-4eee-8cc0-0cd375f50c6d",
      "renderPriority" : "NEUTRAL",
      "renditionMap" : { },
      "type" : "component"
    }, {
      "componentAttributes" : {
        "numberOfArticles" : 5,
        "title" : "Trending Articles",
        "topicId" : "{!topicId}"
      },
      "componentName" : "selfService:topicTrendingArticles42",
      "id" : "ec74a4da-fc2a-4245-aba4-5acce0799c2d",
      "renderPriority" : "NEUTRAL",
      "renditionMap" : { },
      "type" : "component"
    } ],
    "id" : "8d1b8fd8-cda0-46f9-9380-73af2e0929e1",
    "regionName" : "sidebar",
    "type" : "region"
  }, {
    "components" : [ {
      "componentAttributes" : {
        "askCommunityLabel" : "Ask a Question",
        "buttonBgColor" : "",
        "buttonBgHoverColor" : "",
        "buttonBorderColor" : "",
        "buttonRadius" : 0,
        "buttonTextColor" : "",
        "buttonTextHoverColor" : "",
        "buttonTwoBgColor" : "",
        "buttonTwoBgHoverColor" : "",
        "buttonTwoBorderColor" : "",
        "buttonTwoRadius" : 0,
        "buttonTwoTextColor" : "",
        "buttonTwoTextHoverColor" : "",
        "confirmationMessage" : "Got it!",
        "contactSupportLabel" : "Contact Support",
        "followUpPromptLabel" : "Can we close your question?",
        "headerLabel" : "Don't see what you're looking for?",
        "isAskFollowPromptEnabled" : true,
        "isIncludeArticlesEnabled" : false,
        "isIncludeDiscussionsEnabled" : true,
        "isInitialSatisfactionPromptEnabled" : true,
        "isPublisherDeflectionEnabled" : true,
        "maxSuggestions" : 5,
        "satisfactionPromptLabel" : "Did we help to answer your question?",
        "showDetails" : false,
        "showTopics" : true
      },
      "componentName" : "siteforce:napiliFooter",
      "id" : "179731c2-deaa-4ede-a01d-b11f6b20167b",
      "renderPriority" : "NEUTRAL",
      "renditionMap" : { },
      "type" : "component"
    } ],
    "id" : "627d230c-7579-4206-bb21-09d89c12ebc7",
    "regionName" : "footer",
    "type" : "region"
  }, {
    "components" : [ {
      "componentAttributes" : {
        "description" : "",
        "metaTags" : "",
        "title" : "{!Record.Title}"
      },
      "componentName" : "forceCommunity:seoAssistant",
      "id" : "71a17598-c10f-4f16-b5cf-220607355a43",
      "renditionMap" : { },
      "type" : "component"
    } ],
    "id" : "672d0549-2d69-4703-bff9-2706cd83ce2e",
    "regionName" : "sfdcHiddenRegion",
    "type" : "region"
  } ],
  "themeLayoutType" : "Inner",
  "type" : "view",
  "viewType" : "feeditem"
}